pyqgc/__init__.py
pyqgc/_version.py
pyqgc/exceptions.py
pyqgc/qgchelpers.py
pyqgc/qgcmessage.py
pyqgc/qgcreader.py
pyqgc/qgctypes_core.py
pyqgc/qgctypes_get.py
pyqgc/qgctypes_poll.py
pyqgc/qgctypes_set.py
pyqgc-0.2.0.dist-info/licenses/LICENSE
pyqgc-0.2.0.dist-info/METADATA
pyqgc-0.2.0.dist-info/WHEEL
pyqgc-0.2.0.dist-info/top_level.txt
pyqgc-0.2.0.dist-info/RECORD
